get_mac/__init__.py
get_mac/get_mac.py
get_mac/package_version.txt
mac_address_eth-1.1.dist-info/LICENSE
mac_address_eth-1.1.dist-info/METADATA
mac_address_eth-1.1.dist-info/WHEEL
mac_address_eth-1.1.dist-info/entry_points.txt
mac_address_eth-1.1.dist-info/top_level.txt
mac_address_eth-1.1.dist-info/RECORD
