Metadata-Version: 2.1
Name: mac-address-eth
Version: 1.1
Summary: not for all people
Home-page: 
Author: your_name
Author-email: your.email@example.com
Classifier: Programming Language :: Python :: 3
Classifier: License :: OSI Approved :: MIT License
Classifier: Operating System :: OS Independent
Requires-Python: >=3.6
License-File: LICENSE
Requires-Dist: psutil
